instabot_py/__init__.py
instabot_py/__main__.py
instabot_py/default_config.py
instabot_py/instabot.py
instabot_py/sample.instabot.config.yml
instabot_py/persistence/__init__.py
instabot_py/persistence/manager.py
instabot_py/persistence/sql.py
instabot_py-0.7.18.dist-info/LICENSE
instabot_py-0.7.18.dist-info/METADATA
instabot_py-0.7.18.dist-info/WHEEL
instabot_py-0.7.18.dist-info/entry_points.txt
instabot_py-0.7.18.dist-info/top_level.txt
instabot_py-0.7.18.dist-info/RECORD
