Metadata-Version: 2.1
Name: instabot-py
Version: 0.7.18
Summary: Instagram Python Bot
Home-page: https://github.com/instabot-py/instabot.py
Author: Pasha Lev
Author-email: levpasha@gmail.com
License: MIT
Download-URL: https://github.com/instabot-py/instabot.py/tarball/master
Keywords: Instagram bot,Instagram API hack
Platform: UNKNOWN
Classifier: Development Status :: 5 - Production/Stable
Classifier: Intended Audience :: Developers
Classifier: Topic :: Software Development :: Build Tools
Classifier: License :: OSI Approved :: MIT License
Classifier: Programming Language :: Python :: 3
Classifier: Programming Language :: Python :: 3.6
Classifier: Programming Language :: Python :: 3.7
Classifier: Programming Language :: Python :: 3.8
Requires-Python: >3.6.1
